clair_cicd/__init__.py
clair_cicd/assessor.py
clair_cicd/io.py
clair_cicd/jsonschemas.py
clair_cicd/models.py
clair_cicd/jsonschemas/vulnerability.json
clair_cicd/jsonschemas/whitelist.json
clair_cicd-1.0.2.data/scripts/assess-vulnerabilities-risk.py
clair_cicd-1.0.2.dist-info/DESCRIPTION.rst
clair_cicd-1.0.2.dist-info/METADATA
clair_cicd-1.0.2.dist-info/RECORD
clair_cicd-1.0.2.dist-info/WHEEL
clair_cicd-1.0.2.dist-info/metadata.json
clair_cicd-1.0.2.dist-info/top_level.txt
