Metadata-Version: 2.0
Name: clair-cicd
Version: 1.0.2
Summary: Clair CI/CD
Home-page: https://github.com/simonsdave/clair-cicd
Author: Dave Simons
Author-email: simonsdave@gmail.com
Maintainer: Dave Simons
Maintainer-email: simonsdave@gmail.com
License: MIT
Download-URL: https://github.com/simonsdave/clair-cicd/tarball/v1.0.2
Keywords: development,tools
Platform: UNKNOWN
Classifier: Development Status :: 5 - Production/Stable
Classifier: Intended Audience :: Developers
Classifier: Natural Language :: English
Classifier: License :: OSI Approved :: MIT License
Classifier: Operating System :: OS Independent
Classifier: Programming Language :: Python
Classifier: Programming Language :: Python :: 3.7
Classifier: Programming Language :: Python :: Implementation :: CPython
Classifier: Topic :: Software Development :: Libraries :: Python Modules
Requires-Dist: jsonschema (==3.2.0)
